githubapp/__init__.py
githubapp/config.py
githubapp/event_check_run.py
githubapp/exceptions.py
githubapp/webhook_handler.py
githubapp/events/__init__.py
githubapp/events/check_run.py
githubapp/events/check_suite.py
githubapp/events/create.py
githubapp/events/event.py
githubapp/events/issue_comment.py
githubapp/events/issues.py
githubapp/events/pull_request_review.py
githubapp/events/push.py
githubapp/events/release.py
githubapp/events/status.py
githubapp/test_helper/__init__.py
githubapp/test_helper/defaults.json
githubapp/test_helper/spy.py
githubapp/test_helper/test_case.py
github_app_handler-0.28.1.dist-info/LICENSE
github_app_handler-0.28.1.dist-info/METADATA
github_app_handler-0.28.1.dist-info/WHEEL
github_app_handler-0.28.1.dist-info/top_level.txt
github_app_handler-0.28.1.dist-info/RECORD
