Metadata-Version: 2.1
Name: github-app-handler
Version: 0.28.1
Summary: Package to help creates Github Apps.
Author: Heitor Luis Polidoro
License: MIT
Project-URL: Homepage, https://github.com/heitorpolidoro/github-app-handler
Keywords: github,app,githubapp
Classifier: Programming Language :: Python :: 3
Classifier: License :: OSI Approved :: MIT License
Classifier: Operating System :: OS Independent
Requires-Python: >=3.9
License-File: LICENSE
Requires-Dist: PyGithub <3.0
Requires-Dist: pyyaml <7.0
